regvelo/ModelComparison.py
regvelo/__init__.py
regvelo/_constants.py
regvelo/_model.py
regvelo/_module.py
regvelo/datasets/__init__.py
regvelo/datasets/_datasets.py
regvelo/metrics/__init__.py
regvelo/metrics/_abundance_test.py
regvelo/metrics/_cellfate_perturbation.py
regvelo/metrics/_depletion_score.py
regvelo/metrics/_tsi.py
regvelo/metrics/_utils.py
regvelo/plotting/__init__.py
regvelo/plotting/_cellfate_perturbation.py
regvelo/plotting/_commitment_score.py
regvelo/plotting/_depletion_score.py
regvelo/plotting/_simulated_visit_diff.py
regvelo/plotting/_utils.py
regvelo/preprocessing/__init__.py
regvelo/preprocessing/_filter_genes.py
regvelo/preprocessing/_preprocess_data.py
regvelo/preprocessing/_sanity_check.py
regvelo/preprocessing/_set_prior_grn.py
regvelo/tools/_TFScanning_func.py
regvelo/tools/_TFscreening.py
regvelo/tools/__init__.py
regvelo/tools/_in_silico_block_simulation.py
regvelo/tools/_markov_density_simulation.py
regvelo/tools/_perturbation_effect.py
regvelo/tools/_set_output.py
regvelo/tools/_simulated_visit_diff.py
regvelo/tools/_utils.py
regvelo-0.3.0.dist-info/licenses/LICENSE
regvelo-0.3.0.dist-info/METADATA
regvelo-0.3.0.dist-info/WHEEL
regvelo-0.3.0.dist-info/top_level.txt
regvelo-0.3.0.dist-info/RECORD
